<?xml version="1.0" encoding="UTF-8"?>
<!DOCTYPE suite SYSTEM "https://testng.org/testng-1.0.dtd">
<suite thread-count="1" parallel="tests" name="Suite">
	
	<listeners>
		<listener class-name="com.realestatespotpotter.GenericUtilis.IAnnotrans"></listener>
	</listeners>
	<listeners>
		<listener class-name="com.realestatespotpotter.GenericUtilis.ListnerImplimentaion"></listener>
	</listeners>
  <test thread-count="1" parallel="tests" name="Test1">
	  <parameter name="BROWSER" value="chrome"></parameter>
    <classes>
      <class name="AdminLoginPage.Generic_AdminCanRegisterApartment"/>
      <class name="AdminLoginPage.G1_HomeRegAdmin"/>
    </classes>
  </test> <!-- Test -->
  
  
</suite> <!-- Suite -->
